{
  "litres": 1770.0,
  "timestamp": "2025-09-06T21:17:59.328000+00:00",
  "lat": -35.129041,
  "lng": 139.12961,
  "gps_current": {
    "lat": -35.129041,
    "lng": 139.12961,
    "timestamp": "2025-09-06T21:17:59.877652+00:00"
  },
  "breadcrumbs": [
    {
      "lat": -35.129041,
      "lng": 139.129611,
      "timestamp": "2025-09-06T21:17:58.887652+00:00"
    },
    {
      "lat": -35.129041,
      "lng": 139.129611,
      "timestamp": "2025-09-06T21:17:59.085452+00:00"
    },
    {
      "lat": -35.129041,
      "lng": 139.129611,
      "timestamp": "2025-09-06T21:17:59.283652+00:00"
    },
    {
      "lat": -35.129041,
      "lng": 139.129611,
      "timestamp": "2025-09-06T21:17:59.481652+00:00"
    },
    {
      "lat": -35.129041,
      "lng": 139.12961,
      "timestamp": "2025-09-06T21:17:59.679452+00:00"
    },
    {
      "lat": -35.129041,
      "lng": 139.12961,
      "timestamp": "2025-09-06T21:17:59.877652+00:00"
    }
  ],
  "s3_key": "C4DF4028/CAN1_Analog1To4/2025/09/06/00000055_00003252.parquet",
  "gnss_key": "C4DF4028/CAN9_GnssPos/2025/09/06/00000055_00003252.parquet",
  "A1_EMPTY": null,
  "A1_FULL": null,
  "LITRES_EMPTY": 0.0,
  "LITRES_FULL": 600.0
}