{
  "litres": 1710.0,
  "timestamp": "2025-08-31T17:53:59.623600+00:00",
  "lat": -35.129252,
  "lng": 139.129636,
  "gps_current": {
    "lat": -35.129252,
    "lng": 139.129636,
    "timestamp": "2025-08-31T17:53:59.995252+00:00"
  },
  "breadcrumbs": [
    {
      "lat": -35.12925,
      "lng": 139.129642,
      "timestamp": "2025-08-31T17:53:59.005252+00:00"
    },
    {
      "lat": -35.12925,
      "lng": 139.12964,
      "timestamp": "2025-08-31T17:53:59.203252+00:00"
    },
    {
      "lat": -35.129251000000004,
      "lng": 139.129639,
      "timestamp": "2025-08-31T17:53:59.401252+00:00"
    },
    {
      "lat": -35.129252,
      "lng": 139.129638,
      "timestamp": "2025-08-31T17:53:59.599252+00:00"
    },
    {
      "lat": -35.129252,
      "lng": 139.129637,
      "timestamp": "2025-08-31T17:53:59.797302+00:00"
    },
    {
      "lat": -35.129252,
      "lng": 139.129636,
      "timestamp": "2025-08-31T17:53:59.995252+00:00"
    }
  ],
  "s3_key": "C4DF4028/CAN1_Analog1To4/2025/08/31/00000037_00002430.parquet",
  "gnss_key": "C4DF4028/CAN9_GnssPos/2025/08/31/00000037_00002430.parquet",
  "A1_EMPTY": null,
  "A1_FULL": null,
  "LITRES_EMPTY": 0.0,
  "LITRES_FULL": 600.0
}