{
  "litres": 5.0,
  "timestamp": "2025-10-10T05:26:14.027500+00:00",
  "lat": -35.129015,
  "lng": 139.129438,
  "gps_current": {
    "lat": -35.129015,
    "lng": 139.129438,
    "timestamp": "2025-12-19T18:47:59.977602+00:00"
  },
  "breadcrumbs": [
    {
      "lat": -35.129014000000005,
      "lng": 139.129438,
      "timestamp": "2025-12-19T18:47:58.987602+00:00"
    },
    {
      "lat": -35.129014000000005,
      "lng": 139.129438,
      "timestamp": "2025-12-19T18:47:59.185602+00:00"
    },
    {
      "lat": -35.129015,
      "lng": 139.129438,
      "timestamp": "2025-12-19T18:47:59.383652+00:00"
    },
    {
      "lat": -35.129015,
      "lng": 139.129438,
      "timestamp": "2025-12-19T18:47:59.581602+00:00"
    },
    {
      "lat": -35.129015,
      "lng": 139.129438,
      "timestamp": "2025-12-19T18:47:59.779602+00:00"
    },
    {
      "lat": -35.129015,
      "lng": 139.129438,
      "timestamp": "2025-12-19T18:47:59.977602+00:00"
    }
  ],
  "s3_key": "C4DF4028/CAN1_Analog1To4/2025/10/10/00000156_00000832.parquet",
  "gnss_key": "C4DF4028/CAN9_GnssPos/2025/12/19/00000299_00001903.parquet",
  "A1_EMPTY": null,
  "A1_FULL": null,
  "LITRES_EMPTY": 0.0,
  "LITRES_FULL": 600.0
}