{
  "litres": 5.0,
  "timestamp": "2025-10-10T05:26:14.027500+00:00",
  "lat": -35.12912,
  "lng": 139.1295,
  "gps_current": {
    "lat": -35.12912,
    "lng": 139.1295,
    "timestamp": "2025-12-27T19:13:59.951202+00:00"
  },
  "breadcrumbs": [
    {
      "lat": -35.129117,
      "lng": 139.129506,
      "timestamp": "2025-12-27T19:13:58.961202+00:00"
    },
    {
      "lat": -35.129118000000005,
      "lng": 139.129505,
      "timestamp": "2025-12-27T19:13:59.159202+00:00"
    },
    {
      "lat": -35.129118000000005,
      "lng": 139.129504,
      "timestamp": "2025-12-27T19:13:59.357202+00:00"
    },
    {
      "lat": -35.129119,
      "lng": 139.129502,
      "timestamp": "2025-12-27T19:13:59.555202+00:00"
    },
    {
      "lat": -35.129119,
      "lng": 139.129501,
      "timestamp": "2025-12-27T19:13:59.753202+00:00"
    },
    {
      "lat": -35.12912,
      "lng": 139.1295,
      "timestamp": "2025-12-27T19:13:59.951202+00:00"
    }
  ],
  "s3_key": "C4DF4028/CAN1_Analog1To4/2025/10/10/00000156_00000832.parquet",
  "gnss_key": "C4DF4028/CAN9_GnssPos/2025/12/27/00000323_00000475.parquet",
  "A1_EMPTY": null,
  "A1_FULL": null,
  "LITRES_EMPTY": 0.0,
  "LITRES_FULL": 600.0
}