{
  "litres": 970.0,
  "timestamp": "2025-09-22T19:57:59.188050+00:00",
  "lat": -35.129097,
  "lng": 139.129435,
  "gps_current": {
    "lat": -35.129097,
    "lng": 139.129435,
    "timestamp": "2025-09-22T19:57:59.979802+00:00"
  },
  "breadcrumbs": [
    {
      "lat": -35.129096000000004,
      "lng": 139.129437,
      "timestamp": "2025-09-22T19:57:58.989802+00:00"
    },
    {
      "lat": -35.129097,
      "lng": 139.129437,
      "timestamp": "2025-09-22T19:57:59.187702+00:00"
    },
    {
      "lat": -35.129097,
      "lng": 139.129436,
      "timestamp": "2025-09-22T19:57:59.385852+00:00"
    },
    {
      "lat": -35.129097,
      "lng": 139.129436,
      "timestamp": "2025-09-22T19:57:59.583602+00:00"
    },
    {
      "lat": -35.129097,
      "lng": 139.129435,
      "timestamp": "2025-09-22T19:57:59.781802+00:00"
    },
    {
      "lat": -35.129097,
      "lng": 139.129435,
      "timestamp": "2025-09-22T19:57:59.979802+00:00"
    }
  ],
  "s3_key": "C4DF4028/CAN1_Analog1To4/2025/09/22/00000103_00002708.parquet",
  "gnss_key": "C4DF4028/CAN9_GnssPos/2025/09/22/00000103_00002708.parquet",
  "A1_EMPTY": null,
  "A1_FULL": null,
  "LITRES_EMPTY": 0.0,
  "LITRES_FULL": 600.0
}