{
  "litres": 5.0,
  "timestamp": "2025-10-10T05:26:14.027500+00:00",
  "lat": -35.129069,
  "lng": 139.129523,
  "gps_current": {
    "lat": -35.129069,
    "lng": 139.129523,
    "timestamp": "2025-12-24T23:51:59.860452+00:00"
  },
  "breadcrumbs": [
    {
      "lat": -35.129068000000004,
      "lng": 139.129523,
      "timestamp": "2025-12-24T23:51:58.870402+00:00"
    },
    {
      "lat": -35.129068000000004,
      "lng": 139.129522,
      "timestamp": "2025-12-24T23:51:59.068452+00:00"
    },
    {
      "lat": -35.129069,
      "lng": 139.129523,
      "timestamp": "2025-12-24T23:51:59.266302+00:00"
    },
    {
      "lat": -35.129069,
      "lng": 139.129523,
      "timestamp": "2025-12-24T23:51:59.464452+00:00"
    },
    {
      "lat": -35.129069,
      "lng": 139.129523,
      "timestamp": "2025-12-24T23:51:59.662252+00:00"
    },
    {
      "lat": -35.129069,
      "lng": 139.129523,
      "timestamp": "2025-12-24T23:51:59.860452+00:00"
    }
  ],
  "s3_key": "C4DF4028/CAN1_Analog1To4/2025/10/10/00000156_00000832.parquet",
  "gnss_key": "C4DF4028/CAN9_GnssPos/2025/12/24/00000315_00002054.parquet",
  "A1_EMPTY": null,
  "A1_FULL": null,
  "LITRES_EMPTY": 0.0,
  "LITRES_FULL": 600.0
}