{
  "litres": 5.0,
  "timestamp": "2025-10-10T05:26:14.027500+00:00",
  "lat": -35.129068000000004,
  "lng": 139.129121,
  "gps_current": {
    "lat": -35.129068000000004,
    "lng": 139.129121,
    "timestamp": "2026-03-21T19:11:59.900452+00:00"
  },
  "breadcrumbs": [
    {
      "lat": -35.129069,
      "lng": 139.129121,
      "timestamp": "2026-03-21T19:11:58.910452+00:00"
    },
    {
      "lat": -35.129069,
      "lng": 139.129121,
      "timestamp": "2026-03-21T19:11:59.108502+00:00"
    },
    {
      "lat": -35.129069,
      "lng": 139.129121,
      "timestamp": "2026-03-21T19:11:59.306452+00:00"
    },
    {
      "lat": -35.129069,
      "lng": 139.129121,
      "timestamp": "2026-03-21T19:11:59.504452+00:00"
    },
    {
      "lat": -35.129069,
      "lng": 139.129121,
      "timestamp": "2026-03-21T19:11:59.702502+00:00"
    },
    {
      "lat": -35.129068000000004,
      "lng": 139.129121,
      "timestamp": "2026-03-21T19:11:59.900452+00:00"
    }
  ],
  "s3_key": "C4DF4028/CAN1_Analog1To4/2025/10/10/00000156_00000832.parquet",
  "gnss_key": "C4DF4028/CAN9_GnssPos/2026/03/21/00000575_00001834.parquet",
  "A1_EMPTY": null,
  "A1_FULL": null,
  "LITRES_EMPTY": 0.0,
  "LITRES_FULL": 600.0
}