{
  "litres": 965.0,
  "timestamp": "2025-09-25T03:21:59.453750+00:00",
  "lat": -35.129218,
  "lng": 139.129434,
  "gps_current": {
    "lat": -35.129218,
    "lng": 139.129434,
    "timestamp": "2025-09-25T03:21:59.905252+00:00"
  },
  "breadcrumbs": [
    {
      "lat": -35.129224,
      "lng": 139.129436,
      "timestamp": "2025-09-25T03:21:58.915402+00:00"
    },
    {
      "lat": -35.129223,
      "lng": 139.129436,
      "timestamp": "2025-09-25T03:21:59.113302+00:00"
    },
    {
      "lat": -35.129222000000006,
      "lng": 139.129435,
      "timestamp": "2025-09-25T03:21:59.311252+00:00"
    },
    {
      "lat": -35.129220000000004,
      "lng": 139.129435,
      "timestamp": "2025-09-25T03:21:59.509202+00:00"
    },
    {
      "lat": -35.129219,
      "lng": 139.129435,
      "timestamp": "2025-09-25T03:21:59.707152+00:00"
    },
    {
      "lat": -35.129218,
      "lng": 139.129434,
      "timestamp": "2025-09-25T03:21:59.905252+00:00"
    }
  ],
  "s3_key": "C4DF4028/CAN1_Analog1To4/2025/09/25/00000111_00000770.parquet",
  "gnss_key": "C4DF4028/CAN9_GnssPos/2025/09/25/00000111_00000770.parquet",
  "A1_EMPTY": null,
  "A1_FULL": null,
  "LITRES_EMPTY": 0.0,
  "LITRES_FULL": 600.0
}