{
  "litres": 5.0,
  "timestamp": "2025-10-10T05:26:14.027500+00:00",
  "lat": -35.128855,
  "lng": 139.129251,
  "gps_current": {
    "lat": -35.128855,
    "lng": 139.129251,
    "timestamp": "2026-02-01T21:35:59.831702+00:00"
  },
  "breadcrumbs": [
    {
      "lat": -35.128857,
      "lng": 139.129251,
      "timestamp": "2026-02-01T21:35:58.841652+00:00"
    },
    {
      "lat": -35.128856,
      "lng": 139.129251,
      "timestamp": "2026-02-01T21:35:59.039652+00:00"
    },
    {
      "lat": -35.128856,
      "lng": 139.129251,
      "timestamp": "2026-02-01T21:35:59.237652+00:00"
    },
    {
      "lat": -35.128855,
      "lng": 139.129251,
      "timestamp": "2026-02-01T21:35:59.435652+00:00"
    },
    {
      "lat": -35.128855,
      "lng": 139.129251,
      "timestamp": "2026-02-01T21:35:59.633652+00:00"
    },
    {
      "lat": -35.128855,
      "lng": 139.129251,
      "timestamp": "2026-02-01T21:35:59.831702+00:00"
    }
  ],
  "s3_key": "C4DF4028/CAN1_Analog1To4/2025/10/10/00000156_00000832.parquet",
  "gnss_key": "C4DF4028/CAN9_GnssPos/2026/02/01/00000429_00000732.parquet",
  "A1_EMPTY": null,
  "A1_FULL": null,
  "LITRES_EMPTY": 0.0,
  "LITRES_FULL": 600.0
}