{
  "litres": 5.0,
  "timestamp": "2025-10-10T05:26:14.027500+00:00",
  "lat": -35.129090000000005,
  "lng": 139.129238,
  "gps_current": {
    "lat": -35.129090000000005,
    "lng": 139.129238,
    "timestamp": "2026-01-24T22:55:59.838852+00:00"
  },
  "breadcrumbs": [
    {
      "lat": -35.129092,
      "lng": 139.129238,
      "timestamp": "2026-01-24T22:55:58.848702+00:00"
    },
    {
      "lat": -35.129092,
      "lng": 139.129238,
      "timestamp": "2026-01-24T22:55:59.046852+00:00"
    },
    {
      "lat": -35.129091,
      "lng": 139.129238,
      "timestamp": "2026-01-24T22:55:59.244752+00:00"
    },
    {
      "lat": -35.129091,
      "lng": 139.129238,
      "timestamp": "2026-01-24T22:55:59.442852+00:00"
    },
    {
      "lat": -35.129091,
      "lng": 139.129238,
      "timestamp": "2026-01-24T22:55:59.640852+00:00"
    },
    {
      "lat": -35.129090000000005,
      "lng": 139.129238,
      "timestamp": "2026-01-24T22:55:59.838852+00:00"
    }
  ],
  "s3_key": "C4DF4028/CAN1_Analog1To4/2025/10/10/00000156_00000832.parquet",
  "gnss_key": "C4DF4028/CAN9_GnssPos/2026/01/24/00000405_00002701.parquet",
  "A1_EMPTY": null,
  "A1_FULL": null,
  "LITRES_EMPTY": 0.0,
  "LITRES_FULL": 600.0
}