{
  "litres": 5.0,
  "timestamp": "2025-10-10T05:26:14.027500+00:00",
  "lat": -35.128973,
  "lng": 139.129124,
  "gps_current": {
    "lat": -35.128973,
    "lng": 139.129124,
    "timestamp": "2026-01-20T16:17:59.860902+00:00"
  },
  "breadcrumbs": [
    {
      "lat": -35.128973,
      "lng": 139.129125,
      "timestamp": "2026-01-20T16:17:58.870902+00:00"
    },
    {
      "lat": -35.128973,
      "lng": 139.129125,
      "timestamp": "2026-01-20T16:17:59.068902+00:00"
    },
    {
      "lat": -35.128973,
      "lng": 139.129125,
      "timestamp": "2026-01-20T16:17:59.266952+00:00"
    },
    {
      "lat": -35.128973,
      "lng": 139.129125,
      "timestamp": "2026-01-20T16:17:59.464902+00:00"
    },
    {
      "lat": -35.128973,
      "lng": 139.129125,
      "timestamp": "2026-01-20T16:17:59.663052+00:00"
    },
    {
      "lat": -35.128973,
      "lng": 139.129124,
      "timestamp": "2026-01-20T16:17:59.860902+00:00"
    }
  ],
  "s3_key": "C4DF4028/CAN1_Analog1To4/2025/10/10/00000156_00000832.parquet",
  "gnss_key": "C4DF4028/CAN9_GnssPos/2026/01/20/00000392_00003222.parquet",
  "A1_EMPTY": null,
  "A1_FULL": null,
  "LITRES_EMPTY": 0.0,
  "LITRES_FULL": 600.0
}