{
  "litres": 1755.0,
  "timestamp": "2025-09-01T08:49:59.796750+00:00",
  "lat": -35.129196,
  "lng": 139.129635,
  "gps_current": {
    "lat": -35.129196,
    "lng": 139.129635,
    "timestamp": "2025-09-01T08:49:59.987652+00:00"
  },
  "breadcrumbs": [
    {
      "lat": -35.129195,
      "lng": 139.129636,
      "timestamp": "2025-09-01T08:49:58.997502+00:00"
    },
    {
      "lat": -35.129195,
      "lng": 139.129635,
      "timestamp": "2025-09-01T08:49:59.195602+00:00"
    },
    {
      "lat": -35.129195,
      "lng": 139.129636,
      "timestamp": "2025-09-01T08:49:59.393652+00:00"
    },
    {
      "lat": -35.129195,
      "lng": 139.129636,
      "timestamp": "2025-09-01T08:49:59.591652+00:00"
    },
    {
      "lat": -35.129196,
      "lng": 139.129636,
      "timestamp": "2025-09-01T08:49:59.789652+00:00"
    },
    {
      "lat": -35.129196,
      "lng": 139.129635,
      "timestamp": "2025-09-01T08:49:59.987652+00:00"
    }
  ],
  "s3_key": "C4DF4028/CAN1_Analog1To4/2025/09/01/00000039_00002878.parquet",
  "gnss_key": "C4DF4028/CAN9_GnssPos/2025/09/01/00000039_00002878.parquet",
  "A1_EMPTY": null,
  "A1_FULL": null,
  "LITRES_EMPTY": 0.0,
  "LITRES_FULL": 600.0
}