{
  "litres": 5.0,
  "timestamp": "2025-10-10T05:26:14.027500+00:00",
  "lat": -35.129258,
  "lng": 139.129477,
  "gps_current": {
    "lat": -35.129258,
    "lng": 139.129477,
    "timestamp": "2025-12-18T07:59:59.933052+00:00"
  },
  "breadcrumbs": [
    {
      "lat": -35.129257,
      "lng": 139.129478,
      "timestamp": "2025-12-18T07:59:58.943102+00:00"
    },
    {
      "lat": -35.129257,
      "lng": 139.129478,
      "timestamp": "2025-12-18T07:59:59.140852+00:00"
    },
    {
      "lat": -35.129257,
      "lng": 139.129478,
      "timestamp": "2025-12-18T07:59:59.338852+00:00"
    },
    {
      "lat": -35.129257,
      "lng": 139.129478,
      "timestamp": "2025-12-18T07:59:59.537102+00:00"
    },
    {
      "lat": -35.129257,
      "lng": 139.129478,
      "timestamp": "2025-12-18T07:59:59.734902+00:00"
    },
    {
      "lat": -35.129258,
      "lng": 139.129477,
      "timestamp": "2025-12-18T07:59:59.933052+00:00"
    }
  ],
  "s3_key": "C4DF4028/CAN1_Analog1To4/2025/10/10/00000156_00000832.parquet",
  "gnss_key": "C4DF4028/CAN9_GnssPos/2025/12/18/00000295_00000859.parquet",
  "A1_EMPTY": null,
  "A1_FULL": null,
  "LITRES_EMPTY": 0.0,
  "LITRES_FULL": 600.0
}