{
  "litres": 1805.0,
  "timestamp": "2025-09-08T06:49:59.631000+00:00",
  "lat": -35.129261,
  "lng": 139.129546,
  "gps_current": {
    "lat": -35.129261,
    "lng": 139.129546,
    "timestamp": "2025-09-08T06:49:59.945152+00:00"
  },
  "breadcrumbs": [
    {
      "lat": -35.129263,
      "lng": 139.129547,
      "timestamp": "2025-09-08T06:49:58.955052+00:00"
    },
    {
      "lat": -35.129262000000004,
      "lng": 139.129547,
      "timestamp": "2025-09-08T06:49:59.153152+00:00"
    },
    {
      "lat": -35.129262000000004,
      "lng": 139.129547,
      "timestamp": "2025-09-08T06:49:59.350902+00:00"
    },
    {
      "lat": -35.129261,
      "lng": 139.129547,
      "timestamp": "2025-09-08T06:49:59.548902+00:00"
    },
    {
      "lat": -35.129261,
      "lng": 139.129546,
      "timestamp": "2025-09-08T06:49:59.747152+00:00"
    },
    {
      "lat": -35.129261,
      "lng": 139.129546,
      "timestamp": "2025-09-08T06:49:59.945152+00:00"
    }
  ],
  "s3_key": "C4DF4028/CAN1_Analog1To4/2025/09/08/00000060_00000215.parquet",
  "gnss_key": "C4DF4028/CAN9_GnssPos/2025/09/08/00000060_00000215.parquet",
  "A1_EMPTY": null,
  "A1_FULL": null,
  "LITRES_EMPTY": 0.0,
  "LITRES_FULL": 600.0
}