{
  "litres": 5.0,
  "timestamp": "2025-10-10T05:26:14.027500+00:00",
  "lat": -35.129143,
  "lng": 139.128942,
  "gps_current": {
    "lat": -35.129143,
    "lng": 139.128942,
    "timestamp": "2026-01-25T17:11:59.967752+00:00"
  },
  "breadcrumbs": [
    {
      "lat": -35.129142,
      "lng": 139.128941,
      "timestamp": "2026-01-25T17:11:58.977752+00:00"
    },
    {
      "lat": -35.129143,
      "lng": 139.128941,
      "timestamp": "2026-01-25T17:11:59.175752+00:00"
    },
    {
      "lat": -35.129143,
      "lng": 139.128942,
      "timestamp": "2026-01-25T17:11:59.373702+00:00"
    },
    {
      "lat": -35.129143,
      "lng": 139.128942,
      "timestamp": "2026-01-25T17:11:59.571952+00:00"
    },
    {
      "lat": -35.129143,
      "lng": 139.128942,
      "timestamp": "2026-01-25T17:11:59.769902+00:00"
    },
    {
      "lat": -35.129143,
      "lng": 139.128942,
      "timestamp": "2026-01-25T17:11:59.967752+00:00"
    }
  ],
  "s3_key": "C4DF4028/CAN1_Analog1To4/2025/10/10/00000156_00000832.parquet",
  "gnss_key": "C4DF4028/CAN9_GnssPos/2026/01/25/00000407_00003249.parquet",
  "A1_EMPTY": null,
  "A1_FULL": null,
  "LITRES_EMPTY": 0.0,
  "LITRES_FULL": 600.0
}