{
  "litres": 5.0,
  "timestamp": "2025-10-10T05:26:14.027500+00:00",
  "lat": -35.129057,
  "lng": 139.129483,
  "gps_current": {
    "lat": -35.129057,
    "lng": 139.129483,
    "timestamp": "2025-12-01T07:55:59.827902+00:00"
  },
  "breadcrumbs": [
    {
      "lat": -35.129059000000005,
      "lng": 139.129483,
      "timestamp": "2025-12-01T07:55:58.837902+00:00"
    },
    {
      "lat": -35.129059000000005,
      "lng": 139.129483,
      "timestamp": "2025-12-01T07:55:59.035952+00:00"
    },
    {
      "lat": -35.129059000000005,
      "lng": 139.129483,
      "timestamp": "2025-12-01T07:55:59.233852+00:00"
    },
    {
      "lat": -35.129058,
      "lng": 139.129483,
      "timestamp": "2025-12-01T07:55:59.432052+00:00"
    },
    {
      "lat": -35.129058,
      "lng": 139.129483,
      "timestamp": "2025-12-01T07:55:59.629902+00:00"
    },
    {
      "lat": -35.129057,
      "lng": 139.129483,
      "timestamp": "2025-12-01T07:55:59.827902+00:00"
    }
  ],
  "s3_key": "C4DF4028/CAN1_Analog1To4/2025/10/10/00000156_00000832.parquet",
  "gnss_key": "C4DF4028/CAN9_GnssPos/2025/12/01/00000245_00001565.parquet",
  "A1_EMPTY": null,
  "A1_FULL": null,
  "LITRES_EMPTY": 0.0,
  "LITRES_FULL": 600.0
}