{
  "litres": 5.0,
  "timestamp": "2025-10-10T05:26:14.027500+00:00",
  "lat": -35.128981,
  "lng": 139.12925,
  "gps_current": {
    "lat": -35.128981,
    "lng": 139.12925,
    "timestamp": "2026-02-08T23:15:59.829552+00:00"
  },
  "breadcrumbs": [
    {
      "lat": -35.128981,
      "lng": 139.129254,
      "timestamp": "2026-02-08T23:15:58.839402+00:00"
    },
    {
      "lat": -35.128981,
      "lng": 139.129253,
      "timestamp": "2026-02-08T23:15:59.037402+00:00"
    },
    {
      "lat": -35.128981,
      "lng": 139.129252,
      "timestamp": "2026-02-08T23:15:59.235402+00:00"
    },
    {
      "lat": -35.128981,
      "lng": 139.129251,
      "timestamp": "2026-02-08T23:15:59.433402+00:00"
    },
    {
      "lat": -35.128981,
      "lng": 139.129251,
      "timestamp": "2026-02-08T23:15:59.631402+00:00"
    },
    {
      "lat": -35.128981,
      "lng": 139.12925,
      "timestamp": "2026-02-08T23:15:59.829552+00:00"
    }
  ],
  "s3_key": "C4DF4028/CAN1_Analog1To4/2025/10/10/00000156_00000832.parquet",
  "gnss_key": "C4DF4028/CAN9_GnssPos/2026/02/08/00000450_00002222.parquet",
  "A1_EMPTY": null,
  "A1_FULL": null,
  "LITRES_EMPTY": 0.0,
  "LITRES_FULL": 600.0
}