{
  "litres": 5.0,
  "timestamp": "2025-10-10T05:26:14.027500+00:00",
  "lat": -35.129244,
  "lng": 139.129482,
  "gps_current": {
    "lat": -35.129244,
    "lng": 139.129482,
    "timestamp": "2025-11-12T22:55:59.904352+00:00"
  },
  "breadcrumbs": [
    {
      "lat": -35.129245000000004,
      "lng": 139.129485,
      "timestamp": "2025-11-12T22:55:58.914352+00:00"
    },
    {
      "lat": -35.129245000000004,
      "lng": 139.129484,
      "timestamp": "2025-11-12T22:55:59.112352+00:00"
    },
    {
      "lat": -35.129245000000004,
      "lng": 139.129484,
      "timestamp": "2025-11-12T22:55:59.310352+00:00"
    },
    {
      "lat": -35.129244,
      "lng": 139.129483,
      "timestamp": "2025-11-12T22:55:59.508352+00:00"
    },
    {
      "lat": -35.129244,
      "lng": 139.129483,
      "timestamp": "2025-11-12T22:55:59.706352+00:00"
    },
    {
      "lat": -35.129244,
      "lng": 139.129482,
      "timestamp": "2025-11-12T22:55:59.904352+00:00"
    }
  ],
  "s3_key": "C4DF4028/CAN1_Analog1To4/2025/10/10/00000156_00000832.parquet",
  "gnss_key": "C4DF4028/CAN9_GnssPos/2025/11/12/00000189_00002908.parquet",
  "A1_EMPTY": null,
  "A1_FULL": null,
  "LITRES_EMPTY": 0.0,
  "LITRES_FULL": 600.0
}